LICENSE
README.md
pyproject.toml
setup.py
src/PowDeRUL.egg-info/PKG-INFO
src/PowDeRUL.egg-info/SOURCES.txt
src/PowDeRUL.egg-info/dependency_links.txt
src/PowDeRUL.egg-info/requires.txt
src/PowDeRUL.egg-info/top_level.txt
src/powderul/__init__.py
src/powderul/lifetime.py
src/powderul/function/__init__.py
src/powderul/function/counters.py
src/powderul/function/cumul_endommagement.py
src/powderul/function/graphs.py
src/powderul/function/losses.py
src/powderul/function/materials.py
src/powderul/function/matrix.py
src/powderul/function/path_reader.py
src/powderul/function/poly_somme.py
src/powderul/function/temperature.py
src/powderul/function/zth_materials.py